{
  "alertas": [
    {
      "horario": "08:00",
      "categoria": "Profissional",
      "tipo": "Rotina",
      "frequencia": "seg a sex",
      "status": "Ativo",
      "mensagem": "💼 **Início de Bloco de Trabalho:** Vini, virada de bloco de trabalho. Qual é a sua ÚNICA COISA da Curva A de hoje? WhatsApp de trabalho fechado!"
    },
    {
      "horario": "11:30",
      "categoria": "Profissional",
      "tipo": "Lembrete",
      "frequencia": "seg a sex",
      "status": "Ativo",
      "mensagem": "🧭 **Cobrança Horária:** Vini, você está mantendo o foco? Respire fundo, feche abas extras e volte para a entrega Curva A."
    },
    {
      "horario": "14:00",
      "categoria": "Profissional",
      "tipo": "Lembrete",
      "frequencia": "seg a sex",
      "status": "Ativo",
      "mensagem": "🛡️ **Micro-Puxão de Confiabilidade:** Vini, como está a sua integridade hoje? O que você escolheu ignorar para focar na tarefa atual?"
    },
    {
      "horario": "18:00",
      "categoria": "Pessoal",
      "tipo": "Rotina",
      "frequencia": "seg a sex",
      "status": "Ativo",
      "mensagem": "❤️ **Transição Familiar (Zonear o Dia):** HORA DA FAMÍLIA. Vini, desligue o modo produtivo e de trabalho. Laura e Elo precisam de você 100% presente e sem telas."
    },
    {
      "horario": "20:00",
      "categoria": "Pessoal",
      "tipo": "Rotina",
      "frequencia": "seg a sex",
      "status": "Ativo",
      "mensagem": "👨👩👧 **Blindagem Familiar Noturna:** Desconexão total de telas comerciais! Guarde o celular e esteja com as suas meninas."
    },
    {
      "horario": "09:00",
      "categoria": "Pessoal",
      "tipo": "Compromisso",
      "frequencia": "domingo",
      "status": "Ativo",
      "mensagem": "🧭 **Ritual de Planejamento:** Hora de conversar com o Coordenador e Arqueólogo para organizar a semana e mapear a Roda da Vida."
    },
    {
      "horario": "08:00",
      "categoria": "Pessoal",
      "tipo": "Compromisso",
      "frequencia": "unico",
      "status": "Inativo",
      "mensagem": "💳 **Dia de pagar contas!** Abra o app do banco e quite tudo hoje. Sem desculpas."
    }
  ]
}
